LICENSE
README.md
setup.py
get_params/__init__.py
get_params/utils.py
get_params.egg-info/PKG-INFO
get_params.egg-info/SOURCES.txt
get_params.egg-info/dependency_links.txt
get_params.egg-info/top_level.txt