Metadata-Version: 2.1
Name: get-params
Version: 0.1.1
Summary: A package to fetch function arguments from a Python module
Author: Tollef Emil Jørgensen
Author-email: tollefj@gmail.com
Classifier: Programming Language :: Python :: 3
Classifier: License :: OSI Approved :: MIT License
Classifier: Operating System :: OS Independent
Requires-Python: >=3.6
License-File: LICENSE
